fileselection/__init__.py
fileselection/fileselection.py
fileselection-0.3.2.dist-info/AUTHORS.rst
fileselection-0.3.2.dist-info/LICENSE
fileselection-0.3.2.dist-info/METADATA
fileselection-0.3.2.dist-info/WHEEL
fileselection-0.3.2.dist-info/top_level.txt
fileselection-0.3.2.dist-info/RECORD
