Metadata-Version: 2.1
Name: fileselection
Version: 0.3.2
Summary: Persistable lists of selected_paths
Home-page: https://github.com/sjoerdk/fileselection
Author: Sjoerd Kerkstra
Author-email: w.s.kerkstra@gmail.com
License: MIT license
Keywords: fileselection
Platform: UNKNOWN
Classifier: Development Status :: 2 - Pre-Alpha
Classifier: Intended Audience :: Developers
Classifier: License :: OSI Approved :: MIT License
Classifier: Natural Language :: English
Classifier: Programming Language :: Python :: 3.7
Requires-Dist: pyyaml
